btc_price.py
btc_price-0.0.5.dist-info/METADATA
btc_price-0.0.5.dist-info/WHEEL
btc_price-0.0.5.dist-info/top_level.txt
btc_price-0.0.5.dist-info/RECORD
