Metadata-Version: 2.1
Name: btc-price
Version: 0.0.5
Summary: Package to get btc prize in an easy way.
Home-page: https://github.com/HexyeDEV/btc_price
Author: Hexye
License: UNKNOWN
Keywords: Bitcoin price
Platform: UNKNOWN
Classifier: Programming Language :: Python :: 3
Classifier: License :: OSI Approved :: MIT License
Classifier: Operating System :: OS Independent
Requires-Python: >=3.6
